fastapi_extras/__init__.py
fastapi_extras/errors.py
fastapi_extras-0.1.0.dist-info/METADATA
fastapi_extras-0.1.0.dist-info/WHEEL
fastapi_extras-0.1.0.dist-info/RECORD
