Metadata-Version: 2.1
Name: fastapi-extras
Version: 0.1.0
Summary: A collection of utilities for FastAPI
Author: Oluwaseyifunmi Oyefeso
Author-email: oluwaseyifunmi@mafflle.com.ng
Requires-Python: >=3.9,<4.0
Classifier: Programming Language :: Python :: 3
Classifier: Programming Language :: Python :: 3.9
Classifier: Programming Language :: Python :: 3.10
Classifier: Programming Language :: Python :: 3.11
Classifier: Programming Language :: Python :: 3.12
Requires-Dist: fastapi (>=0.110.0,<0.111.0)
Requires-Dist: uvicorn (>=0.29.0,<0.30.0)
